{
  "collection": {
    "info": {
      "_postman_id": "3fe21025-a4b0-4827-a9c8-fd89e5465a81",
      "name": "Presentations Exchange Tutorial",
      "schema": "https://schema.getpostman.com/json/collection/v2.1.0/collection.json"
    },
    "item": [
      {
        "id": "626f4e51-bfb6-44dc-8574-b4f5d3a4f52b",
        "name": "Get Access Token (Issuer)",
        "request": {
          "url": {
            "host": [
              "{{ISSUER_TOKEN_ENDPOINT}}"
            ],
            "query": [],
            "variable": []
          },
          "method": "POST",
          "body": {
            "mode": "raw",
            "raw": "{\n    \"audience\": \"{{ISSUER_TOKEN_AUDIENCE}}\",\n    \"client_id\": \"{{ISSUER_CLIENT_ID}}\",\n    \"client_secret\": \"{{ISSUER_CLIENT_SECRET}}\",\n    \"grant_type\": \"client_credentials\"\n}",
            "options": {
              "raw": {
                "language": "json"
              }
            }
          },
          "auth": {
            "type": "noauth",
            "noauth": []
          }
        },
        "response": [],
        "event": [
          {
            "listen": "test",
            "script": {
              "id": "f6b43bd8-845b-41da-b7ff-19265a916838",
              "type": "text/javascript",
              "exec": [
                "// Token requests are expected to return a `200 Success` response code. Any",
                "// other response code should trigger a failure.",
                "pm.test(\"must return `200 Success` status\", function() {",
                "    pm.response.to.have.status(200);",
                "});",
                "",
                "// The response should include an `access_token` value - this will be presented",
                "// to authenticated API endpoints in the `Authentication` header (see the last",
                "// testing code block for details on how this is persisted).",
                "pm.test(\"response body must include non-empty access_token\", function () {",
                "    const { access_token } = pm.response.json()",
                "    pm.expect(access_token).to.be.a('string').that.is.not.empty;",
                "});",
                "",
                "// The type of `access_token` returned by the token request is expected to be",
                "// `Bearer`.",
                "pm.test(\"response body must represent `Bearer` token\", function() {",
                "    const { token_type } = pm.response.json()",
                "    pm.expect(token_type).to.equal(\"Bearer\");",
                "});",
                "",
                "// The returned data includes an `expires_in` field that indicates time until",
                "// token expiration. Validate that this value is a whole number greater than",
                "// zero, as anything less than or equal to zero means that the `access_token`",
                "// is already expired.",
                "pm.test(\"returned token must expire in the future\", function() {",
                "    const { expires_in } = pm.response.json()",
                "    pm.expect(expires_in).to.be.above(0);",
                "});",
                "",
                "// The returned `access_token` value is persisted as a Postman collection",
                "// variable that can be accessed by other requests in the collection by calling",
                "// `pm.collectionVariables.get(\"issuer_access_token\")`.",
                "pm.test(\"`access_token` persisted to collectionVariables\", function() {",
                "    const { access_token } = pm.response.json()",
                "    pm.collectionVariables.set(\"issuer_access_token\", access_token);",
                "});"
              ],
              "_lastExecutionId": "89f9872c-b56e-4100-b259-37b22cd6d46d"
            }
          }
        ]
      },
      {
        "id": "905784a2-f59a-4f88-899f-16fb6b217b3c",
        "name": "Get Access Token (Verifier)",
        "request": {
          "url": {
            "host": [
              "{{VERIFIER_TOKEN_ENDPOINT}}"
            ],
            "query": [],
            "variable": []
          },
          "method": "POST",
          "body": {
            "mode": "raw",
            "raw": "{\n    \"audience\": \"{{VERIFIER_TOKEN_AUDIENCE}}\",\n    \"client_id\": \"{{VERIFIER_CLIENT_ID}}\",\n    \"client_secret\": \"{{VERIFIER_CLIENT_SECRET}}\",\n    \"grant_type\": \"client_credentials\"\n}",
            "options": {
              "raw": {
                "language": "json"
              }
            }
          },
          "auth": {
            "type": "noauth",
            "noauth": []
          }
        },
        "response": [],
        "event": [
          {
            "listen": "test",
            "script": {
              "id": "ce3cf701-7aba-4d7a-9226-0b8eeb47ea76",
              "type": "text/javascript",
              "exec": [
                "// Token requests are expected to return a `200 Success` response code. Any",
                "// other response code should trigger a failure.",
                "pm.test(\"must return `200 Success` status\", function() {",
                "    pm.response.to.have.status(200);",
                "});",
                "",
                "// The response should include an `access_token` value - this will be presented",
                "// to authenticated API endpoints in the `Authentication` header (see the last",
                "// testing code block for details on how this is persisted).",
                "pm.test(\"response body must include non-empty access_token\", function () {",
                "    const { access_token } = pm.response.json()",
                "    pm.expect(access_token).to.be.a('string').that.is.not.empty;",
                "});",
                "",
                "// The type of `access_token` returned by the token request is expected to be",
                "// `Bearer`.",
                "pm.test(\"response body must represent `Bearer` token\", function() {",
                "    const { token_type } = pm.response.json()",
                "    pm.expect(token_type).to.equal(\"Bearer\");",
                "});",
                "",
                "// The returned data includes an `expires_in` field that indicates time until",
                "// token expiration. Validate that this value is a whole number greater than",
                "// zero, as anything less than or equal to zero means that the `access_token`",
                "// is already expired.",
                "pm.test(\"returned token must expire in the future\", function() {",
                "    const { expires_in } = pm.response.json()",
                "    pm.expect(expires_in).to.be.above(0);",
                "});",
                "",
                "// The returned `access_token` value is persisted as a Postman collection",
                "// variable that can be accessed by other requests in the collection by calling",
                "// `pm.collectionVariables.get(\"verifier_access_token\")`.",
                "pm.test(\"`access_token` persisted to collectionVariables\", function() {",
                "    const { access_token } = pm.response.json()",
                "    pm.collectionVariables.set(\"verifier_access_token\", access_token);",
                "});"
              ],
              "_lastExecutionId": "43128dea-d829-4eb6-910d-5f02a641c774"
            }
          }
        ]
      },
      {
        "id": "d25b3f5d-b5c2-4acb-bdc6-ae3f924b2d6a",
        "name": "Get Issuer Organization DIDs",
        "request": {
          "url": {
            "path": [
              "identifiers",
              "{{ISSUER_ORGANIZATION_DID_WEB}}"
            ],
            "host": [
              "{{ISSUER_API_BASE_URL}}"
            ],
            "query": [],
            "variable": []
          },
          "header": [
            {
              "key": "Accept",
              "value": "application/json"
            }
          ],
          "method": "GET",
          "auth": {
            "type": "bearer",
            "bearer": [
              {
                "type": "string",
                "value": "{{issuer_access_token}}",
                "key": "token"
              }
            ]
          }
        },
        "response": [],
        "event": [
          {
            "listen": "test",
            "script": {
              "id": "23fb8335-9ab2-4d16-94f2-5d0af1f09c3f",
              "type": "text/javascript",
              "exec": [
                "// This endpoint is authenticated. This test will not prevent the request from",
                "// running when the `issuer_access_token` collection variable is missing, but it",
                "// will give an indication of why the request failed in that scenario.",
                "pm.test(\"`issuer_access_token` collection variable must be set\", function () {",
                "    const issuer_access_token = pm.collectionVariables.get(\"issuer_access_token\");",
                "    pm.expect(issuer_access_token).to.be.a('string').that.is.not.empty;",
                "});",
                "",
                "pm.test(\"Status code is 200\", function () {",
                "    pm.response.to.have.status(200);",
                "});",
                "",
                "pm.test(\"must include valid JSON response body\", function() {",
                "    pm.response.json(); // will throw on parse failure",
                "});",
                "",
                "// The response JSON must include a didDocument property that contains the",
                "// resolved DID document.",
                "pm.test(\"didDocument must be present in response body\", function() {",
                "    const jsonData = pm.response.json();",
                "    pm.expect(jsonData).to.have.property('didDocument');",
                "});",
                "",
                "// The DID document must contain an alsoKnownAs property.",
                "pm.test(\"alsoKnownAs MUST be present\", function () {",
                "    const { didDocument } = pm.response.json();",
                "    pm.expect(didDocument).to.have.property('alsoKnownAs');",
                "});",
                "",
                "// The alsoKnownAs property MUST be an array.",
                "pm.test(\"alsoKnownAs MUST be an array\", function() {",
                "    const { alsoKnownAs } = pm.response.json().didDocument;",
                "    pm.expect(alsoKnownAs).to.be.an('array');",
                "});",
                "",
                "// The alsoKnownAs property MUST be a set.",
                "pm.test(\"alsoKnownAs values MUST be unique\", function() {",
                "    const { alsoKnownAs } = pm.response.json().didDocument;",
                "    pm.expect(new Set(alsoKnownAs)).to.have.lengthOf(alsoKnownAs.length);",
                "});",
                "",
                "// The second element of the alsoKnownAs property will be used as a",
                "// credentials_issuer_id for subsequent tests.",
                "pm.test(\"alsoKnownAs[1] must be present\", function() {",
                "    const { alsoKnownAs } = pm.response.json().didDocument;",
                "    pm.expect(alsoKnownAs[1]).to.be.a('string').that.is.not.empty;",
                "});",
                "",
                "// If a verificationMethod property is present, the controller property must",
                "// match the didDocument.id property.",
                "pm.test(\"verification method controller must match did subject\", function() {",
                "    const { didDocument } = pm.response.json();",
                "    const vm = didDocument.verificationMethod || [];",
                "    vm.forEach((m) => pm.expect(m.controller).to.equal(didDocument.id));",
                "});",
                "",
                "// The value of didDocument.alsoKnownAs[1] is persisted as a Postman collection",
                "// variable that can be accessed by other requests in the collection by calling",
                "// pm.collectionVariables.get(\"credential_issuer_id\").",
                "pm.test(\"`credential_issuer_id` persisted to collectionVariables\", function() {",
                "    const { alsoKnownAs } = pm.response.json().didDocument;",
                "    pm.collectionVariables.set(\"credential_issuer_id\", alsoKnownAs[1]);",
                "});"
              ],
              "_lastExecutionId": "a4cfd1d1-fc88-4654-8232-7842a9d27110"
            }
          }
        ],
        "protocolProfileBehavior": {
          "disabledSystemHeaders": {}
        }
      },
      {
        "id": "55131013-aaa1-4a4e-9652-f505388551aa",
        "name": "Get Verifier Organization DIDs",
        "request": {
          "url": {
            "path": [
              "identifiers",
              "{{VERIFIER_ORGANIZATION_DID_WEB}}"
            ],
            "host": [
              "{{VERIFIER_API_BASE_URL}}"
            ],
            "query": [],
            "variable": []
          },
          "header": [
            {
              "key": "Accept",
              "value": "application/json"
            }
          ],
          "method": "GET",
          "auth": {
            "type": "noauth",
            "noauth": []
          }
        },
        "response": [],
        "event": [
          {
            "listen": "test",
            "script": {
              "id": "77c3ef9d-23c1-4db0-a8ee-dcdb08900af5",
              "type": "text/javascript",
              "exec": [
                "pm.test(\"Status code is 200\", function () {",
                "    pm.response.to.have.status(200);",
                "});",
                "",
                "pm.test(\"Issuer makes unauthenticated discovery of verifiers exchange endpoint. `verifier_exchange_endpoint` is persisted to collectionVariables\", function() {",
                "    const { service } = pm.response.json().didDocument;",
                "    pm.collectionVariables.set(\"verifier_exchange_endpoint\", service[0].serviceEndpoint);",
                "});",
                "",
                ""
              ],
              "_lastExecutionId": "871e58fa-e864-402f-9393-4f78e3b7a14b"
            }
          }
        ],
        "protocolProfileBehavior": {
          "disabledSystemHeaders": {}
        }
      },
      {
        "id": "994a86ac-b7d4-49aa-91ec-3d006620e95a",
        "name": "Issue Credential",
        "request": {
          "url": {
            "path": [
              "credentials",
              "issue"
            ],
            "host": [
              "{{ISSUER_API_BASE_URL}}"
            ],
            "query": [],
            "variable": []
          },
          "header": [
            {
              "key": "Accept",
              "value": "application/json"
            }
          ],
          "method": "POST",
          "body": {
            "mode": "raw",
            "raw": "{\n    \"credential\": {\n        \"@context\": [\n            \"https://www.w3.org/2018/credentials/v1\"\n        ],\n        \"id\": \"urn:uuid:{{$randomUUID}}\",\n        \"type\": [\n            \"VerifiableCredential\"\n        ],\n        \"issuer\": \"{{credential_issuer_id}}\",\n        \"issuanceDate\": \"2010-01-01T19:23:24Z\",\n        \"credentialSubject\": {\n            \"id\": \"did:example:123\"\n        }\n    },\n    \"options\": {\n        \"type\": \"Ed25519Signature2018\",\n        \"created\": \"2020-04-02T18:48:36Z\"\n    }\n}",
            "options": {
              "raw": {
                "language": "json"
              }
            }
          },
          "auth": {
            "type": "bearer",
            "bearer": [
              {
                "type": "string",
                "value": "{{issuer_access_token}}",
                "key": "token"
              }
            ]
          }
        },
        "response": [],
        "event": [
          {
            "listen": "test",
            "script": {
              "id": "9f932c60-1351-4645-bc7b-6ce6ec1aacb5",
              "type": "text/javascript",
              "exec": [
                "// This endpoint is authenticated. This test will not prevent the request from",
                "// running when the `issuer_access_token` collection variable is missing, but it",
                "// will give an indication of why the request failed in that scenario.",
                "pm.test(\"`issuer_access_token` collection variable must be set\", function () {",
                "    const issuer_access_token = pm.collectionVariables.get(\"issuer_access_token\");",
                "    pm.expect(issuer_access_token).to.be.a('string').that.is.not.empty;",
                "});",
                "",
                "pm.test(\"`credential_issuer_id` collection variable must be set\", function () {",
                "    const credential_issuer_id = pm.collectionVariables.get(\"credential_issuer_id\");",
                "    pm.expect(credential_issuer_id).to.be.a('string').that.is.not.empty;",
                "});",
                "",
                "pm.test(\"must return `201 Created` status\", function () {",
                "    pm.response.to.have.status(201);",
                "});",
                "",
                "// Verifiable credential must be made available to later requests",
                "pm.test(\"`verifiable_credential` persisted to collectionVariables\", function() {",
                "    const verifiable_credential = JSON.stringify(pm.response.json());",
                "    pm.collectionVariables.set(\"verifiable_credential\", verifiable_credential);",
                "})"
              ],
              "_lastExecutionId": "c1974211-4942-4900-a5ec-43e0dba776dc"
            }
          },
          {
            "listen": "prerequest",
            "script": {
              "id": "b5e637c1-9f89-44ad-953a-15c28c50a4dc",
              "type": "text/javascript",
              "exec": [
                ""
              ],
              "_lastExecutionId": "5d6edb95-0b86-4861-8d97-06d87ea9f374"
            }
          }
        ]
      },
      {
        "id": "32c4a1a5-f96e-4daf-b3f9-144f86fe984d",
        "name": "Initiate Exchange",
        "request": {
          "url": {
            "path": [
              "presentations",
              "available"
            ],
            "host": [
              "{{verifier_exchange_endpoint}}"
            ],
            "query": [],
            "variable": []
          },
          "header": [
            {
              "key": "Accept",
              "value": "application/json"
            }
          ],
          "method": "POST",
          "body": {
            "mode": "raw",
            "raw": "{\n  \"query\": [\n    {\n      \"type\": \"QueryByExample\",\n      \"credentialQuery\": [\n        {\n          \"type\": [\n            \"VerifiableCredential\"\n          ],\n          \"reason\": \"We want to present credentials.\"\n        }\n      ]\n    }\n  ]\n}",
            "options": {
              "raw": {
                "language": "json"
              }
            }
          },
          "auth": {
            "type": "bearer",
            "bearer": [
              {
                "type": "string",
                "value": "{{verifier_access_token}}",
                "key": "token"
              }
            ]
          }
        },
        "response": [],
        "event": [
          {
            "listen": "test",
            "script": {
              "id": "40c0af70-9893-4220-b64c-8efaa98ee6d8",
              "type": "text/javascript",
              "exec": [
                "// This endpoint is authenticated. This test will not prevent the request from",
                "// running when the `verifier_access_token` collection variable is missing, but",
                "// it will give an indication of why the request failed in that scenario.",
                "pm.test(\"`verifier_access_token` collection variable must be set\", function () {",
                "    const verifier_access_token = pm.collectionVariables.get(\"verifier_access_token\");",
                "    pm.expect(verifier_access_token).to.be.a('string').that.is.not.empty;",
                "});",
                "",
                "// The expected response code for a \"Presentations Available\" request is",
                "// `200 Success`.",
                "pm.test(\"must return `200 Success` status\", function () {",
                "    pm.response.to.have.status(200);",
                "});",
                "",
                "// The response body must include a \"domain\" property.",
                "pm.test(\"response must include 'domain' property\", function() {",
                "    const { domain } = pm.response.json()",
                "    pm.expect(domain).to.be.a('string').that.is.not.empty;",
                "    // Domain must be made available to later requests",
                "    pm.collectionVariables.set(\"domain\", domain);",
                "});",
                "",
                "// The response body must include a \"challenge\" property.",
                "pm.test(\"response must include 'challenge' property\", function() {",
                "    const { challenge } = pm.response.json()",
                "    pm.expect(challenge).to.be.a('string').that.is.not.empty;",
                "    // Challenge must be made available to later requests",
                "    pm.collectionVariables.set(\"challenge\", challenge);",
                "});",
                ""
              ],
              "_lastExecutionId": "a8616543-28fe-447c-8eb1-784829e2b526"
            }
          }
        ]
      },
      {
        "id": "2b20a589-f49d-4713-98cf-28465a1ada91",
        "name": "Sign Presentation",
        "request": {
          "url": {
            "path": [
              "presentations",
              "prove"
            ],
            "host": [
              "{{ISSUER_API_BASE_URL}}"
            ],
            "query": [],
            "variable": []
          },
          "header": [
            {
              "key": "Accept",
              "value": "application/json"
            }
          ],
          "method": "POST",
          "body": {
            "mode": "raw",
            "raw": "{\n    \"presentation\": {\n        \"@context\": [\n            \"https://www.w3.org/2018/credentials/v1\"\n        ],\n        \"type\": [\n            \"VerifiablePresentation\"\n        ],\n        \"holder\": \"{{credential_issuer_id}}\",\n        \"verifiableCredential\": [\n            {{verifiable_credential}}\n        ]\n    },\n    \"options\": {\n        \"domain\": \"{{domain}}\",\n        \"challenge\": \"{{challenge}}\"\n    }\n}",
            "options": {
              "raw": {
                "language": "json"
              }
            }
          },
          "auth": {
            "type": "bearer",
            "bearer": [
              {
                "type": "string",
                "value": "{{issuer_access_token}}",
                "key": "token"
              }
            ]
          }
        },
        "response": [],
        "event": [
          {
            "listen": "test",
            "script": {
              "id": "47e931da-5c4d-431d-a005-566b905a0dae",
              "type": "text/javascript",
              "exec": [
                "// This endpoint is authenticated. This test will not prevent the request from",
                "// running when the `issuer_access_token` collection variable is missing, but it",
                "// will give an indication of why the request failed in that scenario.",
                "pm.test(\"`issuer_access_token` collection variable must be set\", function () {",
                "    const issuer_access_token = pm.collectionVariables.get(\"issuer_access_token\");",
                "    pm.expect(issuer_access_token).to.be.a('string').that.is.not.empty;",
                "});",
                "",
                "// Credential issuer id is a required element item used in the request body",
                "pm.test(\"`credential_issuer_id` collection variable must be set\", function () {",
                "    const credential_issuer_id = pm.collectionVariables.get(\"credential_issuer_id\");",
                "    pm.expect(credential_issuer_id).to.be.a('string').that.is.not.empty;",
                "});",
                "",
                "// Verifiable credential is a required element item used in the request body",
                "pm.test(\"`verifiable_credential` collection variable must be set\", function () {",
                "    const verifiable_credential = pm.collectionVariables.get(\"verifiable_credential\");",
                "    pm.expect(verifiable_credential).to.be.a('string').that.is.not.empty;",
                "});",
                "",
                "// Domain is a required element item used in the request body",
                "pm.test(\"`domain` collection variable must be set\", function () {",
                "    const domain = pm.collectionVariables.get(\"domain\");",
                "    pm.expect(domain).to.be.a('string').that.is.not.empty;",
                "});",
                "",
                "// Challenge is a required element item used in the request body",
                "pm.test(\"`challenge` collection variable must be set\", function () {",
                "    const challenge = pm.collectionVariables.get(\"challenge\");",
                "    pm.expect(challenge).to.be.a('string').that.is.not.empty;",
                "});",
                "",
                "// The expected response code for a \"Sign Presentation\" request is",
                "// `201 Success`.",
                "pm.test(\"must return `201 Success` status\", function () {",
                "    pm.response.to.have.status(201);",
                "});",
                "",
                "// Verifiable presentation must be made available to later requests",
                "pm.test(\"`verifiable_presentation` persisted to collectionVariables\", function() {",
                "    const verifiable_presentation = JSON.stringify(pm.response.json());",
                "    pm.collectionVariables.set(\"verifiable_presentation\", verifiable_presentation);",
                "})"
              ],
              "_lastExecutionId": "6fcc79af-e8f0-4008-8889-74e67fb24713"
            }
          }
        ]
      },
      {
        "id": "8df8e487-2f71-4e6c-bdbd-d71f7f2718f2",
        "name": "Complete Exchange",
        "request": {
          "url": {
            "path": [
              "presentations",
              "submissions"
            ],
            "host": [
              "{{verifier_exchange_endpoint}}"
            ],
            "query": [],
            "variable": []
          },
          "header": [
            {
              "key": "Accept",
              "value": "application/json"
            }
          ],
          "method": "POST",
          "body": {
            "mode": "raw",
            "raw": "{{verifiable_presentation}}",
            "options": {
              "raw": {
                "language": "json"
              }
            }
          },
          "auth": {
            "type": "bearer",
            "bearer": [
              {
                "type": "string",
                "value": "{{verifier_access_token}}",
                "key": "token"
              }
            ]
          }
        },
        "response": [],
        "event": [
          {
            "listen": "test",
            "script": {
              "id": "f3308cbb-0fb8-4942-81e3-bab6c4b7db9d",
              "type": "text/javascript",
              "exec": [
                "// This endpoint is authenticated. This test will not prevent the request from",
                "// running when the `verifier_access_token` collection variable is missing, but",
                "// it will give an indication of why the request failed in that scenario.",
                "pm.test(\"`verifier_access_token` collection variable must be set\", function () {",
                "    const verifier_access_token = pm.collectionVariables.get(\"verifier_access_token\");",
                "    pm.expect(verifier_access_token).to.be.a('string').that.is.not.empty;",
                "});",
                "",
                "// The expected response code for a \"Complete Exchange\" request is",
                "// `200 Success`.",
                "pm.test(\"must return `200 Success` status\", function () {",
                "    pm.response.to.have.status(200);",
                "});",
                "",
                "// Response should confirm the submission is accepted.",
                "pm.test(\"verification response should be 'true'\", function() {",
                "    const { verified } = pm.response.json()",
                "    pm.expect(verified).to.be.true;",
                "});"
              ],
              "_lastExecutionId": "3dd83d6e-6347-4b89-b613-5ae579a60860"
            }
          }
        ]
      }
    ]
  },
  "run": {
    "stats": {
      "iterations": {
        "total": 1,
        "pending": 0,
        "failed": 0
      },
      "items": {
        "total": 8,
        "pending": 0,
        "failed": 0
      },
      "scripts": {
        "total": 25,
        "pending": 0,
        "failed": 0
      },
      "prerequests": {
        "total": 8,
        "pending": 0,
        "failed": 0
      },
      "requests": {
        "total": 8,
        "pending": 0,
        "failed": 0
      },
      "tests": {
        "total": 8,
        "pending": 0,
        "failed": 0
      },
      "assertions": {
        "total": 40,
        "pending": 0,
        "failed": 2
      },
      "testScripts": {
        "total": 16,
        "pending": 0,
        "failed": 0
      },
      "prerequestScripts": {
        "total": 9,
        "pending": 0,
        "failed": 0
      }
    },
    "timings": {
      "responseAverage": 203.25,
      "responseMin": 75,
      "responseMax": 444,
      "responseSd": 152.80113710309882,
      "dnsAverage": 0,
      "dnsMin": 0,
      "dnsMax": 0,
      "dnsSd": 0,
      "firstByteAverage": 0,
      "firstByteMin": 0,
      "firstByteMax": 0,
      "firstByteSd": 0,
      "started": 1652492436778,
      "completed": 1652492438777
    },
    "executions": [
      {
        "id": "626f4e51-bfb6-44dc-8574-b4f5d3a4f52b",
        "cursor": {
          "position": 0,
          "iteration": 0,
          "length": 8,
          "cycles": 1,
          "empty": false,
          "eof": false,
          "bof": true,
          "cr": false,
          "ref": "86ded62a-4dbb-4def-8993-9966d105455a",
          "httpRequestId": "b3b5ddf0-e68c-49ef-aba2-3f4cb8835902"
        },
        "item": {
          "id": "626f4e51-bfb6-44dc-8574-b4f5d3a4f52b",
          "name": "Get Access Token (Issuer)"
        },
        "response": {
          "id": "55015171-1876-4e94-b8da-3fcd2ac155d3",
          "status": "OK",
          "code": 200,
          "responseTime": 444,
          "responseSize": 975
        },
        "assertions": [
          {
            "assertion": "must return `200 Success` status",
            "skipped": false
          },
          {
            "assertion": "response body must include non-empty access_token",
            "skipped": false
          },
          {
            "assertion": "response body must represent `Bearer` token",
            "skipped": false
          },
          {
            "assertion": "returned token must expire in the future",
            "skipped": false
          },
          {
            "assertion": "`access_token` persisted to collectionVariables",
            "skipped": false
          }
        ]
      },
      {
        "id": "905784a2-f59a-4f88-899f-16fb6b217b3c",
        "cursor": {
          "ref": "922e024f-c91e-4bce-896d-65cda10357dd",
          "length": 8,
          "cycles": 1,
          "position": 1,
          "iteration": 0,
          "httpRequestId": "b800c6ee-7584-4abc-96ba-36f57abd6ade"
        },
        "item": {
          "id": "905784a2-f59a-4f88-899f-16fb6b217b3c",
          "name": "Get Access Token (Verifier)"
        },
        "response": {
          "id": "0ae15031-2c3c-4309-9efe-777eccfbd83a",
          "status": "OK",
          "code": 200,
          "responseTime": 430,
          "responseSize": 975
        },
        "assertions": [
          {
            "assertion": "must return `200 Success` status",
            "skipped": false
          },
          {
            "assertion": "response body must include non-empty access_token",
            "skipped": false
          },
          {
            "assertion": "response body must represent `Bearer` token",
            "skipped": false
          },
          {
            "assertion": "returned token must expire in the future",
            "skipped": false
          },
          {
            "assertion": "`access_token` persisted to collectionVariables",
            "skipped": false
          }
        ]
      },
      {
        "id": "d25b3f5d-b5c2-4acb-bdc6-ae3f924b2d6a",
        "cursor": {
          "ref": "372c6cb9-1019-480e-b264-ee65c9ef0cac",
          "length": 8,
          "cycles": 1,
          "position": 2,
          "iteration": 0,
          "httpRequestId": "72a2a806-e5b1-4fc0-85e3-84771b186a63"
        },
        "item": {
          "id": "d25b3f5d-b5c2-4acb-bdc6-ae3f924b2d6a",
          "name": "Get Issuer Organization DIDs"
        },
        "response": {
          "id": "c5e3ab50-8b9c-4046-ae2c-70b6a6fdb3ad",
          "status": "OK",
          "code": 200,
          "responseTime": 308,
          "responseSize": 766
        },
        "assertions": [
          {
            "assertion": "`issuer_access_token` collection variable must be set",
            "skipped": false
          },
          {
            "assertion": "Status code is 200",
            "skipped": false
          },
          {
            "assertion": "must include valid JSON response body",
            "skipped": false
          },
          {
            "assertion": "didDocument must be present in response body",
            "skipped": false
          },
          {
            "assertion": "alsoKnownAs MUST be present",
            "skipped": false
          },
          {
            "assertion": "alsoKnownAs MUST be an array",
            "skipped": false
          },
          {
            "assertion": "alsoKnownAs values MUST be unique",
            "skipped": false
          },
          {
            "assertion": "alsoKnownAs[1] must be present",
            "skipped": false
          },
          {
            "assertion": "verification method controller must match did subject",
            "skipped": false
          },
          {
            "assertion": "`credential_issuer_id` persisted to collectionVariables",
            "skipped": false
          }
        ]
      },
      {
        "id": "55131013-aaa1-4a4e-9652-f505388551aa",
        "cursor": {
          "ref": "ed47f2b7-2c2d-4403-869e-fba8a71b73b5",
          "length": 8,
          "cycles": 1,
          "position": 3,
          "iteration": 0,
          "httpRequestId": "a76601c1-cb7a-47e8-aa5d-ec34356399bf"
        },
        "item": {
          "id": "55131013-aaa1-4a4e-9652-f505388551aa",
          "name": "Get Verifier Organization DIDs"
        },
        "response": {
          "id": "e9273c98-ac76-4287-9b9b-dfc37860d93c",
          "status": "OK",
          "code": 200,
          "responseTime": 84,
          "responseSize": 675
        },
        "assertions": [
          {
            "assertion": "Status code is 200",
            "skipped": false
          },
          {
            "assertion": "Issuer makes unauthenticated discovery of verifiers exchange endpoint. `verifier_exchange_endpoint` is persisted to collectionVariables",
            "skipped": false
          }
        ]
      },
      {
        "id": "994a86ac-b7d4-49aa-91ec-3d006620e95a",
        "cursor": {
          "ref": "8b5c5aac-70b8-42b9-b912-980dbf58da56",
          "length": 8,
          "cycles": 1,
          "position": 4,
          "iteration": 0,
          "httpRequestId": "add568a2-d7ae-4f7f-8520-9b2f7555528a"
        },
        "item": {
          "id": "994a86ac-b7d4-49aa-91ec-3d006620e95a",
          "name": "Issue Credential"
        },
        "response": {
          "id": "d0d30ba5-a57d-4d74-8908-823ad3c09016",
          "status": "Created",
          "code": 201,
          "responseTime": 94,
          "responseSize": 679
        },
        "assertions": [
          {
            "assertion": "`issuer_access_token` collection variable must be set",
            "skipped": false
          },
          {
            "assertion": "`credential_issuer_id` collection variable must be set",
            "skipped": false
          },
          {
            "assertion": "must return `201 Created` status",
            "skipped": false
          },
          {
            "assertion": "`verifiable_credential` persisted to collectionVariables",
            "skipped": false
          }
        ]
      },
      {
        "id": "32c4a1a5-f96e-4daf-b3f9-144f86fe984d",
        "cursor": {
          "ref": "9305b09b-684a-4adb-b879-26667a41ea9b",
          "length": 8,
          "cycles": 1,
          "position": 5,
          "iteration": 0,
          "httpRequestId": "5edc24ef-d527-475f-9fa4-13fa7d88bd6d"
        },
        "item": {
          "id": "32c4a1a5-f96e-4daf-b3f9-144f86fe984d",
          "name": "Initiate Exchange"
        },
        "response": {
          "id": "0c8ea9df-7187-44a6-a23b-4333de548b4f",
          "status": "OK",
          "code": 200,
          "responseTime": 75,
          "responseSize": 282
        },
        "assertions": [
          {
            "assertion": "`verifier_access_token` collection variable must be set",
            "skipped": false
          },
          {
            "assertion": "must return `200 Success` status",
            "skipped": false
          },
          {
            "assertion": "response must include 'domain' property",
            "skipped": false
          },
          {
            "assertion": "response must include 'challenge' property",
            "skipped": false
          }
        ]
      },
      {
        "id": "2b20a589-f49d-4713-98cf-28465a1ada91",
        "cursor": {
          "ref": "b7001806-57f1-4d1b-a140-d802ef158fbd",
          "length": 8,
          "cycles": 1,
          "position": 6,
          "iteration": 0,
          "httpRequestId": "42ac748d-ef4f-4c7f-a7cf-1b7c6e660285"
        },
        "item": {
          "id": "2b20a589-f49d-4713-98cf-28465a1ada91",
          "name": "Sign Presentation"
        },
        "response": {
          "id": "90169e7f-b5e9-4d3d-8655-a194d6484a29",
          "status": "Created",
          "code": 201,
          "responseTime": 113,
          "responseSize": 1320
        },
        "assertions": [
          {
            "assertion": "`issuer_access_token` collection variable must be set",
            "skipped": false
          },
          {
            "assertion": "`credential_issuer_id` collection variable must be set",
            "skipped": false
          },
          {
            "assertion": "`verifiable_credential` collection variable must be set",
            "skipped": false
          },
          {
            "assertion": "`domain` collection variable must be set",
            "skipped": false
          },
          {
            "assertion": "`challenge` collection variable must be set",
            "skipped": false
          },
          {
            "assertion": "must return `201 Success` status",
            "skipped": false
          },
          {
            "assertion": "`verifiable_presentation` persisted to collectionVariables",
            "skipped": false
          }
        ]
      },
      {
        "id": "8df8e487-2f71-4e6c-bdbd-d71f7f2718f2",
        "cursor": {
          "ref": "8a11fada-4d8e-419b-8598-1cb033853d91",
          "length": 8,
          "cycles": 1,
          "position": 7,
          "iteration": 0,
          "httpRequestId": "8a8f8026-7903-46a2-b45c-aac78d11ab58"
        },
        "item": {
          "id": "8df8e487-2f71-4e6c-bdbd-d71f7f2718f2",
          "name": "Complete Exchange"
        },
        "response": {
          "id": "3bea3b25-c92b-4dcd-a8c0-f26ed5a843a9",
          "status": "Bad Request",
          "code": 400,
          "responseTime": 78,
          "responseSize": 99
        },
        "assertions": [
          {
            "assertion": "`verifier_access_token` collection variable must be set",
            "skipped": false
          },
          {
            "assertion": "must return `200 Success` status",
            "skipped": false,
            "error": {
              "name": "AssertionError",
              "index": 1,
              "test": "must return `200 Success` status",
              "message": "expected response to have status code 200 but got 400",
              "stack": "AssertionError: expected response to have status code 200 but got 400\n   at Object.eval sandbox-script.js:2:8)"
            }
          },
          {
            "assertion": "verification response should be 'true'",
            "skipped": false,
            "error": {
              "name": "AssertionError",
              "index": 2,
              "test": "verification response should be 'true'",
              "message": "expected undefined to be true",
              "stack": "AssertionError: expected undefined to be true\n   at Object.eval sandbox-script.js:3:8)"
            }
          }
        ]
      }
    ]
  }
}