{
  "collection": {
    "info": {
      "_postman_id": "8ce11389-4715-4913-ac8a-339aceeb0d65",
      "name": "Credentials Revocation Tutorial",
      "schema": "https://schema.getpostman.com/json/collection/v2.1.0/collection.json"
    },
    "item": [
      {
        "id": "ee736a82-9205-459e-b090-a7a07c2d2c6c",
        "name": "Get Access Token",
        "request": {
          "url": {
            "host": [
              "{{TOKEN_ENDPOINT}}"
            ],
            "query": [],
            "variable": []
          },
          "method": "POST",
          "body": {
            "mode": "urlencoded",
            "urlencoded": [
              {
                "key": "audience",
                "value": "{{TOKEN_AUDIENCE}}"
              },
              {
                "key": "client_id",
                "value": "{{CLIENT_ID}}"
              },
              {
                "key": "client_secret",
                "value": "{{CLIENT_SECRET}}"
              },
              {
                "key": "grant_type",
                "value": "client_credentials"
              },
              {
                "key": "scope",
                "value": "{{CLIENT_SCOPE}}"
              }
            ]
          }
        },
        "response": [],
        "event": [
          {
            "listen": "test",
            "script": {
              "id": "ff7cb0fc-c203-4975-b2af-58205e219d72",
              "type": "text/javascript",
              "exec": [
                "// Token requests are expected to return a `200 Success` response code. Any",
                "// other response code should trigger a failure.",
                "pm.test(\"must return `200 Success` status\", function() {",
                "    pm.response.to.have.status(200);",
                "});",
                "",
                "// The response should include an `access_token` value - this will be presented",
                "// to authenticated API endpoints in the `Authentication` header (see the last",
                "// testing code block for details on how this is persisted).",
                "pm.test(\"response body must include non-empty access_token\", function () {",
                "    const { access_token } = pm.response.json()",
                "    pm.expect(access_token).to.be.a('string').that.is.not.empty;",
                "});",
                "",
                "// The type of `access_token` returned by the token request is expected to be",
                "// `Bearer`.",
                "pm.test(\"response body must represent `Bearer` token\", function() {",
                "    const { token_type } = pm.response.json()",
                "    pm.expect(token_type).to.equal(\"Bearer\");",
                "});",
                "",
                "// The returned data includes an `expires_in` field that indicates time until",
                "// token expiration. Validate that this value is a whole number greater than",
                "// zero, as anything less than or equal to zero means that the `access_token`",
                "// is already expired.",
                "pm.test(\"returned token must expire in the future\", function() {",
                "    const { expires_in } = pm.response.json()",
                "    pm.expect(expires_in).to.be.above(0);",
                "});",
                "",
                "// The returned `access_token` value is persisted as a Postman collection",
                "// variable that can be accessed by other requests in the collection by calling",
                "// `pm.collectionVariables.get(\"access_token\")`.",
                "pm.test(\"`access_token` persisted to collectionVariables\", function() {",
                "    const { access_token } = pm.response.json()",
                "    pm.collectionVariables.set(\"access_token\", access_token);",
                "});"
              ],
              "_lastExecutionId": "bc47f651-948f-41e8-a045-fad55c45803a"
            }
          }
        ]
      },
      {
        "id": "d60a18e3-4efa-4828-9bee-92a4d594c01d",
        "name": "Get Organization DIDs",
        "request": {
          "url": {
            "path": [
              "identifiers",
              "{{ORGANIZATION_DID_WEB}}"
            ],
            "host": [
              "{{API_BASE_URL}}"
            ],
            "query": [],
            "variable": []
          },
          "header": [
            {
              "key": "Accept",
              "value": "application/json"
            }
          ],
          "method": "GET",
          "auth": {
            "type": "bearer",
            "bearer": [
              {
                "type": "string",
                "value": "{{access_token}}",
                "key": "token"
              }
            ]
          }
        },
        "response": [],
        "event": [
          {
            "listen": "test",
            "script": {
              "id": "da880da7-ae66-468c-bd4e-8cd6eb484f85",
              "type": "text/javascript",
              "exec": [
                "// This endpoint is authenticated. This test will not prevent the request from",
                "// running when the `access_token` collection variable is missing, but it will",
                "// give an indication of why the request failed in that scenario.",
                "pm.test(\"`access_token` collection variable must be set\", function () {",
                "    const access_token = pm.collectionVariables.get(\"access_token\");",
                "    pm.expect(access_token).to.be.a('string').that.is.not.empty;",
                "});",
                "",
                "pm.test(\"Status code is 200\", function () {",
                "    pm.response.to.have.status(200);",
                "});",
                "",
                "pm.test(\"must include valid JSON response body\", function() {",
                "    pm.response.json(); // will throw on parse failure",
                "});",
                "",
                "// The response JSON must include a didDocument property that contains the",
                "// resolved DID document.",
                "pm.test(\"didDocument must be present in response body\", function() {",
                "    const jsonData = pm.response.json();",
                "    pm.expect(jsonData).to.have.property('didDocument');",
                "});",
                "",
                "// If a verificationMethod property is present, the controller property must",
                "// match the didDocument.id property.",
                "pm.test(\"verification method controller must match did subject\", function() {",
                "    const { didDocument } = pm.response.json();",
                "    const vm = didDocument.verificationMethod || [];",
                "    vm.forEach((m) => pm.expect(m.controller).to.equal(didDocument.id));",
                "});",
                "",
                "// The value of didDocument.id is persisted as a Postman collection variable",
                "// that can be accessed by other requests in the collection by calling",
                "// pm.collectionVariables.get(\"credential_issuer_id\").",
                "pm.test(\"`credential_issuer_id` persisted to collectionVariables\", function() {",
                "    const { didDocument } = pm.response.json();",
                "    pm.collectionVariables.set(\"credential_issuer_id\", didDocument.id);",
                "});"
              ],
              "_lastExecutionId": "69bddac3-8ada-4955-a2c8-28f9346b1b75"
            }
          }
        ],
        "protocolProfileBehavior": {
          "disabledSystemHeaders": {}
        }
      },
      {
        "id": "44e5eb78-20a2-4664-ad72-43dc42b2afe3",
        "name": "Issue Credential",
        "request": {
          "url": {
            "path": [
              "credentials",
              "issue"
            ],
            "host": [
              "{{API_BASE_URL}}"
            ],
            "query": [],
            "variable": []
          },
          "header": [
            {
              "key": "Accept",
              "value": "application/json"
            }
          ],
          "method": "POST",
          "body": {
            "mode": "raw",
            "raw": "{\n    \"credential\": {\n        \"@context\": [\n            \"https://www.w3.org/2018/credentials/v1\",\n            \"https://w3id.org/vc-revocation-list-2020/v1\"\n        ],\n        \"id\": \"urn:uuid:{{$randomUUID}}\",\n        \"type\": [\n            \"VerifiableCredential\"\n        ],\n        \"issuer\": \"{{credential_issuer_id}}\",\n        \"issuanceDate\": \"{{$isoTimestamp}}\",\n        \"credentialSubject\": {\n            \"id\": \"did:example:123\"\n        }\n    },\n    \"options\": {\n        \"type\": \"Ed25519Signature2018\",\n        \"created\": \"{{$isoTimestamp}}\",\n        \"credentialStatus\": {\n            \"type\": \"RevocationList2020Status\"\n        }\n    }\n}",
            "options": {
              "raw": {
                "language": "json"
              }
            }
          },
          "auth": {
            "type": "bearer",
            "bearer": [
              {
                "type": "string",
                "value": "{{access_token}}",
                "key": "token"
              }
            ]
          }
        },
        "response": [],
        "event": [
          {
            "listen": "test",
            "script": {
              "id": "0445bcb7-116e-4f24-9a94-95ce0d0e0c7f",
              "type": "text/javascript",
              "exec": [
                "pm.test(\"`access_token` collection variable must be set\", function () {",
                "    pm.expect(pm.collectionVariables.get(\"access_token\")).to.not.be.undefined;",
                "});",
                "",
                "pm.test(\"`credential_issuer_id` collection variable must be set\", function () {",
                "    pm.expect(pm.collectionVariables.get(\"credential_issuer_id\")).to.not.be.undefined;",
                "});",
                "",
                "pm.test(\"must return `201 Created` status\", function () {",
                "    pm.response.to.have.status(201);",
                "});",
                "",
                "// Verifiable credential must be made available to later requests",
                "pm.test(\"`verifiable_credential` persisted to collectionVariables\", function() {",
                "    const {verifiableCredential} = pm.response.json();",
                "    pm.collectionVariables.set(\"verifiable_credential\", JSON.stringify(verifiableCredential));",
                "});"
              ],
              "_lastExecutionId": "4f506226-2e5d-46aa-a665-adee74aeae3d"
            }
          },
          {
            "listen": "prerequest",
            "script": {
              "id": "9a60c6cb-7a20-4166-861d-a4afa248a36e",
              "type": "text/javascript",
              "exec": [
                ""
              ],
              "_lastExecutionId": "429a4258-6e1c-4ab2-8fee-c342ba01815d"
            }
          }
        ]
      },
      {
        "id": "982905b4-ac9d-4859-afd9-84c57df03cb1",
        "name": "Verify Credential",
        "request": {
          "url": {
            "path": [
              "credentials",
              "verify"
            ],
            "host": [
              "{{API_BASE_URL}}"
            ],
            "query": [],
            "variable": []
          },
          "header": [
            {
              "key": "Accept",
              "value": "application/json"
            }
          ],
          "method": "POST",
          "body": {
            "mode": "raw",
            "raw": "{\n    \"verifiableCredential\": {{verifiable_credential}}\n}",
            "options": {
              "raw": {
                "language": "json"
              }
            }
          },
          "auth": {
            "type": "bearer",
            "bearer": [
              {
                "type": "string",
                "value": "{{access_token}}",
                "key": "token"
              }
            ]
          }
        },
        "response": [],
        "event": [
          {
            "listen": "test",
            "script": {
              "id": "cccf8528-3655-4602-8d27-9da2fd17424d",
              "type": "text/javascript",
              "exec": [
                "// The `/credentials/verify` endpoint is authenticated. This test will not",
                "// prevent the request from running when the `access_token` collection variable",
                "// is missing, but it will give an indication of why the request failed in that",
                "// scenario.",
                "pm.test(\"`access_token` collection variable must be set\", function () {",
                "    pm.expect(pm.collectionVariables.get(\"access_token\")).to.not.be.undefined;",
                "});",
                "",
                "// The `verifiable_credential` from the \"Credentials Issue\" request is used to",
                "// populate part of the request body. If this collection variable is missing,",
                "// the request will not be prevented, but this test will raise an error that",
                "// will help to identify the problem.",
                "pm.test(\"`verifiable_credential` collection variable must be set\", function () {",
                "    pm.expect(pm.collectionVariables.get(\"verifiable_credential\")).to.not.be.undefined;",
                "});",
                "",
                "// The expected response code for a \"Credentials Verify\" request is",
                "// `200 Success`.",
                "pm.test(\"must return `200 Success` status\", function () {",
                "    pm.response.to.have.status(200);",
                "});",
                "",
                "// The verification should succeed.",
                "pm.test(\"verification should be successful\", function() {",
                "    const { verified } = pm.response.json()",
                "    pm.expect(verified).to.be.true;",
                "});"
              ],
              "_lastExecutionId": "8ac36e51-ee73-4af8-9f5a-ce69805b4a5e"
            }
          }
        ]
      },
      {
        "id": "76403768-8a08-4d85-ae8b-59c3b4117aff",
        "name": "Revoke Credential",
        "request": {
          "url": {
            "path": [
              "credentials",
              "status"
            ],
            "host": [
              "{{API_BASE_URL}}"
            ],
            "query": [],
            "variable": []
          },
          "header": [
            {
              "key": "Accept",
              "value": "application/json"
            }
          ],
          "method": "POST",
          "body": {
            "mode": "raw",
            "raw": "{\n    \"credentialId\": \"{{verifiable_credential_id}}\",\n    \"credentialStatus\": [\n        {\n            \"type\": \"RevocationList2020Status\",\n            \"status\": \"1\"\n        }\n    ]\n}",
            "options": {
              "raw": {
                "language": "json"
              }
            }
          },
          "auth": {
            "type": "bearer",
            "bearer": [
              {
                "type": "string",
                "value": "{{access_token}}",
                "key": "token"
              }
            ]
          }
        },
        "response": [],
        "event": [
          {
            "listen": "prerequest",
            "script": {
              "id": "116a56ee-367c-417a-abf5-2c3ee8bd60b9",
              "type": "text/javascript",
              "exec": [
                "// Extract credential ID from verifiable credential",
                "let verifiable_credential_id;",
                "try {",
                "    const { id } = JSON.parse(pm.collectionVariables.get(\"verifiable_credential\"));",
                "    pm.collectionVariables.set('verifiable_credential_id', id)",
                "} catch {}",
                ""
              ],
              "_lastExecutionId": "23b9e08a-7440-4106-be31-e65b8babeec9"
            }
          },
          {
            "listen": "test",
            "script": {
              "id": "be308d3c-7bd7-4d39-adfd-bac014f11af2",
              "type": "text/javascript",
              "exec": [
                "// The `/credentials/status` endpoint is authenticated. This test will not",
                "// prevent the request from running when the `access_token` collection variable",
                "// is missing, but it will give an indication of why the request failed in that",
                "// scenario.",
                "pm.test(\"`access_token` collection variable must be set\", function () {",
                "    pm.expect(pm.collectionVariables.get(\"access_token\")).to.not.be.undefined;",
                "});",
                "",
                "// Verifiable credential ID is a required element item used in the request body",
                "pm.test(\"`verifiable_credential_id` local variable must be set\", function () {",
                "    pm.expect(\"verifiable_credential\").to.be.a('string').that.is.not.empty;",
                "});",
                "",
                "// The expected response code for a \"Revoke Credentials\" request is `200 Success`",
                "pm.test(\"must return `200 Success` status\", function () {",
                "    pm.response.to.have.status(200);",
                "});"
              ],
              "_lastExecutionId": "f42e8f7f-b248-47f2-b4e4-b5a958d1a4fe"
            }
          }
        ]
      },
      {
        "id": "4aea9459-4dd0-4008-afab-7fad0d0b5364",
        "name": "Verify Revocation",
        "request": {
          "url": {
            "path": [
              "credentials",
              "verify"
            ],
            "host": [
              "{{API_BASE_URL}}"
            ],
            "query": [],
            "variable": []
          },
          "header": [
            {
              "key": "Accept",
              "value": "application/json"
            }
          ],
          "method": "POST",
          "body": {
            "mode": "raw",
            "raw": "{\n    \"verifiableCredential\": {{verifiable_credential}}\n}",
            "options": {
              "raw": {
                "language": "json"
              }
            }
          },
          "auth": {
            "type": "bearer",
            "bearer": [
              {
                "type": "string",
                "value": "{{access_token}}",
                "key": "token"
              }
            ]
          }
        },
        "response": [],
        "event": [
          {
            "listen": "test",
            "script": {
              "id": "1cad2ba5-e8db-410f-9cdc-08b100fcdc28",
              "type": "text/javascript",
              "exec": [
                "// The `/credentials/verify` endpoint is authenticated. This test will not",
                "// prevent the request from running when the `access_token` collection variable",
                "// is missing, but it will give an indication of why the request failed in that",
                "// scenario.",
                "pm.test(\"`access_token` collection variable must be set\", function () {",
                "    pm.expect(pm.collectionVariables.get(\"access_token\")).to.not.be.undefined;",
                "});",
                "",
                "// The `verifiable_credential` from the \"Credentials Issue\" request is used to",
                "// populate part of the request body. If this collection variable is missing,",
                "// the request will not be prevented, but this test will raise an error that",
                "// will help to identify the problem.",
                "pm.test(\"`verifiable_credential` collection variable must be set\", function () {",
                "    pm.expect(pm.collectionVariables.get(\"verifiable_credential\")).to.not.be.undefined;",
                "});",
                "",
                "// The expected response code for a \"Credentials Verify\" request is",
                "// `200 Success`.",
                "pm.test(\"must return `200 Success` status\", function () {",
                "    pm.response.to.have.status(200);",
                "});",
                "",
                "// Checks should have errors",
                "//pm.test(\"Checks should have credentialStatus errors\", function() {",
                "//    const { errors } = pm.response.json();",
                "//    pm.expect(errors).to.include(\"credentialStatus\");",
                "//});",
                "",
                "// Confirm error",
                "pm.test(\"Checks should have credentialStatus errors\", function() {",
                "    let obj = pm.response.json().verifications.find(e => e.title === \"Revocation\");",
                "    pm.expect(obj.status).to.eql(\"bad\");",
                "});",
                "",
                "",
                ""
              ],
              "_lastExecutionId": "de83aeff-c786-4b46-968a-7bd73c259eba"
            }
          }
        ]
      }
    ]
  },
  "run": {
    "stats": {
      "iterations": {
        "total": 1,
        "pending": 0,
        "failed": 0
      },
      "items": {
        "total": 6,
        "pending": 0,
        "failed": 0
      },
      "scripts": {
        "total": 20,
        "pending": 0,
        "failed": 0
      },
      "prerequests": {
        "total": 6,
        "pending": 0,
        "failed": 0
      },
      "requests": {
        "total": 6,
        "pending": 0,
        "failed": 0
      },
      "tests": {
        "total": 6,
        "pending": 0,
        "failed": 0
      },
      "assertions": {
        "total": 26,
        "pending": 0,
        "failed": 1
      },
      "testScripts": {
        "total": 12,
        "pending": 0,
        "failed": 0
      },
      "prerequestScripts": {
        "total": 8,
        "pending": 0,
        "failed": 0
      }
    },
    "timings": {
      "responseAverage": 173.16666666666666,
      "responseMin": 32,
      "responseMax": 394,
      "responseSd": 144.4384720987529,
      "dnsAverage": 0,
      "dnsMin": 0,
      "dnsMax": 0,
      "dnsSd": 0,
      "firstByteAverage": 0,
      "firstByteMin": 0,
      "firstByteMax": 0,
      "firstByteSd": 0,
      "started": 1697849606750,
      "completed": 1697849608026
    },
    "executions": [
      {
        "id": "ee736a82-9205-459e-b090-a7a07c2d2c6c",
        "cursor": {
          "position": 0,
          "iteration": 0,
          "length": 6,
          "cycles": 1,
          "empty": false,
          "eof": false,
          "bof": true,
          "cr": false,
          "ref": "1810fb2b-424e-4d00-a33e-a5186d9743d1",
          "httpRequestId": "95d26b69-42a6-4f64-b3c9-8f12dcec22c1"
        },
        "item": {
          "id": "ee736a82-9205-459e-b090-a7a07c2d2c6c",
          "name": "Get Access Token"
        },
        "response": {
          "id": "912e8137-b911-4c6e-9ce2-e54adba9113b",
          "status": "OK",
          "code": 200,
          "responseTime": 394,
          "responseSize": 1339
        },
        "assertions": [
          {
            "assertion": "must return `200 Success` status",
            "skipped": false
          },
          {
            "assertion": "response body must include non-empty access_token",
            "skipped": false
          },
          {
            "assertion": "response body must represent `Bearer` token",
            "skipped": false
          },
          {
            "assertion": "returned token must expire in the future",
            "skipped": false
          },
          {
            "assertion": "`access_token` persisted to collectionVariables",
            "skipped": false
          }
        ]
      },
      {
        "id": "d60a18e3-4efa-4828-9bee-92a4d594c01d",
        "cursor": {
          "ref": "5b38093a-f76d-4483-9da9-ea498a198019",
          "length": 6,
          "cycles": 1,
          "position": 1,
          "iteration": 0,
          "httpRequestId": "30bb1a35-7b75-4334-8a3b-f8bdf0e9cc3e"
        },
        "item": {
          "id": "d60a18e3-4efa-4828-9bee-92a4d594c01d",
          "name": "Get Organization DIDs"
        },
        "response": {
          "id": "7073c15f-1984-40d8-ae4a-d18b86647b1b",
          "status": "OK",
          "code": 200,
          "responseTime": 32,
          "responseSize": 2450
        },
        "assertions": [
          {
            "assertion": "`access_token` collection variable must be set",
            "skipped": false
          },
          {
            "assertion": "Status code is 200",
            "skipped": false
          },
          {
            "assertion": "must include valid JSON response body",
            "skipped": false
          },
          {
            "assertion": "didDocument must be present in response body",
            "skipped": false
          },
          {
            "assertion": "verification method controller must match did subject",
            "skipped": false
          },
          {
            "assertion": "`credential_issuer_id` persisted to collectionVariables",
            "skipped": false
          }
        ]
      },
      {
        "id": "44e5eb78-20a2-4664-ad72-43dc42b2afe3",
        "cursor": {
          "ref": "4943bf28-0009-420d-855e-d6deb6e656b9",
          "length": 6,
          "cycles": 1,
          "position": 2,
          "iteration": 0,
          "httpRequestId": "2c685396-ebff-4e26-a23f-601fce1cca0f"
        },
        "item": {
          "id": "44e5eb78-20a2-4664-ad72-43dc42b2afe3",
          "name": "Issue Credential"
        },
        "response": {
          "id": "e3a55ec1-872e-4e8d-8494-d2516c0ab672",
          "status": "Created",
          "code": 201,
          "responseTime": 356,
          "responseSize": 976
        },
        "assertions": [
          {
            "assertion": "`access_token` collection variable must be set",
            "skipped": false
          },
          {
            "assertion": "`credential_issuer_id` collection variable must be set",
            "skipped": false
          },
          {
            "assertion": "must return `201 Created` status",
            "skipped": false
          },
          {
            "assertion": "`verifiable_credential` persisted to collectionVariables",
            "skipped": false
          }
        ]
      },
      {
        "id": "982905b4-ac9d-4859-afd9-84c57df03cb1",
        "cursor": {
          "ref": "c18f11be-1b0e-4675-854f-e592c73d48f5",
          "length": 6,
          "cycles": 1,
          "position": 3,
          "iteration": 0,
          "httpRequestId": "5a45a4e0-2d5f-457e-9c02-d336afd978f4"
        },
        "item": {
          "id": "982905b4-ac9d-4859-afd9-84c57df03cb1",
          "name": "Verify Credential"
        },
        "response": {
          "id": "319d0cda-3832-4a3b-ab2e-0c9cb22b37d9",
          "status": "OK",
          "code": 200,
          "responseTime": 83,
          "responseSize": 153
        },
        "assertions": [
          {
            "assertion": "`access_token` collection variable must be set",
            "skipped": false
          },
          {
            "assertion": "`verifiable_credential` collection variable must be set",
            "skipped": false
          },
          {
            "assertion": "must return `200 Success` status",
            "skipped": false
          },
          {
            "assertion": "verification should be successful",
            "skipped": false
          }
        ]
      },
      {
        "id": "76403768-8a08-4d85-ae8b-59c3b4117aff",
        "cursor": {
          "ref": "daf97845-2c2d-470b-b7e7-3d612c4d00eb",
          "length": 6,
          "cycles": 1,
          "position": 4,
          "iteration": 0,
          "httpRequestId": "955ef598-b47d-4d9f-8607-38d3bf9415d3"
        },
        "item": {
          "id": "76403768-8a08-4d85-ae8b-59c3b4117aff",
          "name": "Revoke Credential"
        },
        "response": {
          "id": "e8519f99-575d-4328-811e-77bbc62fb53c",
          "status": "OK",
          "code": 200,
          "responseTime": 81,
          "responseSize": 0
        },
        "assertions": [
          {
            "assertion": "`access_token` collection variable must be set",
            "skipped": false
          },
          {
            "assertion": "`verifiable_credential_id` local variable must be set",
            "skipped": false
          },
          {
            "assertion": "must return `200 Success` status",
            "skipped": false
          }
        ]
      },
      {
        "id": "4aea9459-4dd0-4008-afab-7fad0d0b5364",
        "cursor": {
          "ref": "2511dec8-53ea-48ba-b3aa-f7525322346c",
          "length": 6,
          "cycles": 1,
          "position": 5,
          "iteration": 0,
          "httpRequestId": "f7d4043b-b81c-482b-95e8-e1774931509a"
        },
        "item": {
          "id": "4aea9459-4dd0-4008-afab-7fad0d0b5364",
          "name": "Verify Revocation"
        },
        "response": {
          "id": "363dc321-afc0-42c9-b150-e2a282850ee2",
          "status": "OK",
          "code": 200,
          "responseTime": 93,
          "responseSize": 153
        },
        "assertions": [
          {
            "assertion": "`access_token` collection variable must be set",
            "skipped": false
          },
          {
            "assertion": "`verifiable_credential` collection variable must be set",
            "skipped": false
          },
          {
            "assertion": "must return `200 Success` status",
            "skipped": false
          },
          {
            "assertion": "Checks should have credentialStatus errors",
            "skipped": false,
            "error": {
              "name": "AssertionError",
              "index": 3,
              "test": "Checks should have credentialStatus errors",
              "message": "expected 'good' to deeply equal 'bad'",
              "stack": "AssertionError: expected 'good' to deeply equal 'bad'\n   at Object.eval sandbox-script.js:4:6)"
            }
          }
        ]
      }
    ]
  }
}