{
  "collection": {
    "info": {
      "_postman_id": "ff0fff7b-56e1-4a32-a638-2b67cfcfad71",
      "name": "DID Web Discovery Tutorial",
      "schema": "https://schema.getpostman.com/json/collection/v2.1.0/collection.json"
    },
    "item": [
      {
        "id": "e6de08b1-23ef-4dd9-85b0-3f7bc7a564e2",
        "name": "Get Access Token",
        "request": {
          "url": {
            "host": [
              "{{TOKEN_ENDPOINT}}"
            ],
            "query": [],
            "variable": []
          },
          "method": "POST",
          "body": {
            "mode": "urlencoded",
            "urlencoded": [
              {
                "key": "audience",
                "value": "{{TOKEN_AUDIENCE}}"
              },
              {
                "key": "client_id",
                "value": "{{CLIENT_ID}}"
              },
              {
                "key": "client_secret",
                "value": "{{CLIENT_SECRET}}"
              },
              {
                "key": "grant_type",
                "value": "client_credentials"
              },
              {
                "key": "scope",
                "value": "{{CLIENT_SCOPE}}"
              }
            ]
          }
        },
        "response": [],
        "event": [
          {
            "listen": "test",
            "script": {
              "id": "08cc9985-8834-4960-88f0-83c1432cc688",
              "type": "text/javascript",
              "exec": [
                "// Token requests are expected to return a `200 Success` response code. Any",
                "// other response code should trigger a failure.",
                "pm.test(\"must return `200 Success` status\", function() {",
                "    pm.response.to.have.status(200);",
                "})",
                "",
                "// The response should include an `access_token` value - this will be presented",
                "// to authenticated API endpoints in the `Authentication` header (see the last",
                "// testing code block for details on how this is persisted).",
                "pm.test(\"response body must include non-empty access_token\", function () {",
                "    const { access_token } = pm.response.json()",
                "    pm.expect(access_token).to.be.a('string').that.is.not.empty;",
                "});",
                "",
                "// The type of `access_token` returned by the token request is expected to be",
                "// `Bearer`.",
                "pm.test(\"response body must represent `Bearer` token\", function() {",
                "    const { token_type } = pm.response.json()",
                "    pm.expect(token_type).to.equal(\"Bearer\");",
                "});",
                "",
                "// The returned data includes an `expires_in` field that indicates time until",
                "// token expiration. Validate that this value is a whole number greater than",
                "// zero, as anything less than or equal to zero means that the `access_token`",
                "// is already expired.",
                "pm.test(\"returned token must expire in the future\", function() {",
                "    const { expires_in } = pm.response.json()",
                "    pm.expect(expires_in).to.be.above(0);",
                "});",
                "",
                "// The returned `access_token` value is persisted as a Postman collection",
                "// variable that can be accessed by other requests in the collection by calling",
                "// `pm.collectionVariables.get(\"access_token\")`.",
                "pm.test(\"`access_token` persisted to collectionVariables\", function() {",
                "    const { access_token } = pm.response.json()",
                "    pm.collectionVariables.set(\"access_token\", access_token);",
                "});"
              ],
              "_lastExecutionId": "5d6af856-9b07-4b03-93a1-ba08a25abad2"
            }
          }
        ]
      },
      {
        "id": "7c8d53af-841c-442d-9f3a-502a4ab40abc",
        "name": "Get Organization DIDs",
        "request": {
          "url": {
            "path": [
              "identifiers",
              "{{ORGANIZATION_DID_WEB}}"
            ],
            "host": [
              "{{API_BASE_URL}}"
            ],
            "query": [],
            "variable": []
          },
          "header": [
            {
              "key": "Accept",
              "value": "application/json"
            }
          ],
          "method": "GET",
          "auth": {
            "type": "bearer",
            "bearer": [
              {
                "type": "string",
                "value": "{{access_token}}",
                "key": "token"
              }
            ]
          }
        },
        "response": [],
        "event": [
          {
            "listen": "test",
            "script": {
              "id": "caa7deb0-4c26-4362-8f7e-b3981a98b34a",
              "type": "text/javascript",
              "exec": [
                "pm.test(\"Status code is 200\", function () {",
                "    pm.response.to.have.status(200);",
                "});",
                "",
                "pm.test(\"must include valid JSON response body\", function() {",
                "    pm.response.json(); // will throw on parse failure",
                "});",
                "",
                "// The response JSON must include a didDocument property that contains the",
                "// resolved DID document.",
                "pm.test(\"didDocument must be present in response body\", function() {",
                "    const jsonData = pm.response.json();",
                "    pm.expect(jsonData).to.have.property('didDocument');",
                "});",
                "",
                "// Service array is used to look up traceability API service endpoint",
                "pm.test(\"Response must include 'service' array\", function() {",
                "    const { service } = pm.response.json().didDocument;",
                "    pm.expect(service).to.be.an('array').that.is.not.empty;",
                "});",
                "",
                "// Service array must be correctly defined in DID document",
                "pm.test(\"'service' array must define Traceability API service endpoint\", function() {",
                "    const { service } = pm.response.json().didDocument;",
                "    const entry = service.find((s) => s.type == \"TraceabilityAPI\");",
                "    pm.expect(entry).to.be.an('object').that.is.not.empty;",
                "    pm.expect(entry.serviceEndpoint).to.be.a('string').that.is.not.empty;",
                "});",
                "",
                "// If a verificationMethod property is present, the controller property must",
                "// match the didDocument.id property.",
                "pm.test(\"verification method controller must match did subject\", function() {",
                "    const { didDocument } = pm.response.json();",
                "    const vm = didDocument.verificationMethod || [];",
                "    vm.forEach((m) => pm.expect(m.controller).to.equal(didDocument.id));",
                "});"
              ],
              "_lastExecutionId": "aa723b06-5af3-4963-8bbc-e38943ab3a15"
            }
          }
        ],
        "protocolProfileBehavior": {
          "disabledSystemHeaders": {}
        }
      }
    ]
  },
  "run": {
    "stats": {
      "iterations": {
        "total": 1,
        "pending": 0,
        "failed": 0
      },
      "items": {
        "total": 2,
        "pending": 0,
        "failed": 0
      },
      "scripts": {
        "total": 2,
        "pending": 0,
        "failed": 0
      },
      "prerequests": {
        "total": 2,
        "pending": 0,
        "failed": 0
      },
      "requests": {
        "total": 2,
        "pending": 0,
        "failed": 0
      },
      "tests": {
        "total": 2,
        "pending": 0,
        "failed": 0
      },
      "assertions": {
        "total": 11,
        "pending": 0,
        "failed": 0
      },
      "testScripts": {
        "total": 2,
        "pending": 0,
        "failed": 0
      },
      "prerequestScripts": {
        "total": 0,
        "pending": 0,
        "failed": 0
      }
    },
    "timings": {
      "responseAverage": 428.5,
      "responseMin": 93,
      "responseMax": 764,
      "responseSd": 335.5,
      "dnsAverage": 0,
      "dnsMin": 0,
      "dnsMax": 0,
      "dnsSd": 0,
      "firstByteAverage": 0,
      "firstByteMin": 0,
      "firstByteMax": 0,
      "firstByteSd": 0,
      "started": 1690074785783,
      "completed": 1690074786714
    },
    "executions": [
      {
        "id": "e6de08b1-23ef-4dd9-85b0-3f7bc7a564e2",
        "cursor": {
          "position": 0,
          "iteration": 0,
          "length": 2,
          "cycles": 1,
          "empty": false,
          "eof": false,
          "bof": true,
          "cr": false,
          "ref": "c40cedae-d26f-4e06-b120-519ca1f2adf0",
          "httpRequestId": "d384d685-e32e-4c48-b38e-b9daf6114213"
        },
        "item": {
          "id": "e6de08b1-23ef-4dd9-85b0-3f7bc7a564e2",
          "name": "Get Access Token"
        },
        "response": {
          "id": "4c5b800b-045b-4f2a-9ae5-0ddf9814bcfb",
          "status": "OK",
          "code": 200,
          "responseTime": 764,
          "responseSize": 957
        },
        "assertions": [
          {
            "assertion": "must return `200 Success` status",
            "skipped": false
          },
          {
            "assertion": "response body must include non-empty access_token",
            "skipped": false
          },
          {
            "assertion": "response body must represent `Bearer` token",
            "skipped": false
          },
          {
            "assertion": "returned token must expire in the future",
            "skipped": false
          },
          {
            "assertion": "`access_token` persisted to collectionVariables",
            "skipped": false
          }
        ]
      },
      {
        "id": "7c8d53af-841c-442d-9f3a-502a4ab40abc",
        "cursor": {
          "ref": "5e785603-d3fd-4399-a361-a092bcf5fb21",
          "length": 2,
          "cycles": 1,
          "position": 1,
          "iteration": 0,
          "httpRequestId": "504f5198-665a-40bc-af67-6471942bd20c"
        },
        "item": {
          "id": "7c8d53af-841c-442d-9f3a-502a4ab40abc",
          "name": "Get Organization DIDs"
        },
        "response": {
          "id": "b7e6b636-a13c-4cb7-9381-6c3f7f75bdcf",
          "status": "OK",
          "code": 200,
          "responseTime": 93,
          "responseSize": 1028
        },
        "assertions": [
          {
            "assertion": "Status code is 200",
            "skipped": false
          },
          {
            "assertion": "must include valid JSON response body",
            "skipped": false
          },
          {
            "assertion": "didDocument must be present in response body",
            "skipped": false
          },
          {
            "assertion": "Response must include 'service' array",
            "skipped": false
          },
          {
            "assertion": "'service' array must define Traceability API service endpoint",
            "skipped": false
          },
          {
            "assertion": "verification method controller must match did subject",
            "skipped": false
          }
        ]
      }
    ]
  }
}