{
  "collection": {
    "info": {
      "_postman_id": "7573cc79-8d9a-4dfd-8b2e-1c4079752653",
      "name": "DID Web Discovery Tutorial",
      "schema": "https://schema.getpostman.com/json/collection/v2.1.0/collection.json"
    },
    "item": [
      {
        "id": "6496ad91-3674-42dd-8275-3ea13324834f",
        "name": "Get Access Token",
        "request": {
          "url": {
            "host": [
              "{{TOKEN_ENDPOINT}}"
            ],
            "query": [],
            "variable": []
          },
          "method": "POST",
          "body": {
            "mode": "urlencoded",
            "urlencoded": [
              {
                "key": "audience",
                "value": "{{TOKEN_AUDIENCE}}"
              },
              {
                "key": "client_id",
                "value": "{{CLIENT_ID}}"
              },
              {
                "key": "client_secret",
                "value": "{{CLIENT_SECRET}}"
              },
              {
                "key": "grant_type",
                "value": "client_credentials"
              },
              {
                "key": "scope",
                "value": "{{CLIENT_SCOPE}}"
              }
            ]
          }
        },
        "response": [],
        "event": [
          {
            "listen": "test",
            "script": {
              "id": "eec13954-9779-4bb6-8974-cf6cd9107b35",
              "type": "text/javascript",
              "exec": [
                "// Token requests are expected to return a `200 Success` response code. Any",
                "// other response code should trigger a failure.",
                "pm.test(\"must return `200 Success` status\", function() {",
                "    pm.response.to.have.status(200);",
                "})",
                "",
                "// The response should include an `access_token` value - this will be presented",
                "// to authenticated API endpoints in the `Authentication` header (see the last",
                "// testing code block for details on how this is persisted).",
                "pm.test(\"response body must include non-empty access_token\", function () {",
                "    const { access_token } = pm.response.json()",
                "    pm.expect(access_token).to.be.a('string').that.is.not.empty;",
                "});",
                "",
                "// The type of `access_token` returned by the token request is expected to be",
                "// `Bearer`.",
                "pm.test(\"response body must represent `Bearer` token\", function() {",
                "    const { token_type } = pm.response.json()",
                "    pm.expect(token_type).to.equal(\"Bearer\");",
                "});",
                "",
                "// The returned data includes an `expires_in` field that indicates time until",
                "// token expiration. Validate that this value is a whole number greater than",
                "// zero, as anything less than or equal to zero means that the `access_token`",
                "// is already expired.",
                "pm.test(\"returned token must expire in the future\", function() {",
                "    const { expires_in } = pm.response.json()",
                "    pm.expect(expires_in).to.be.above(0);",
                "});",
                "",
                "// The returned `access_token` value is persisted as a Postman collection",
                "// variable that can be accessed by other requests in the collection by calling",
                "// `pm.collectionVariables.get(\"access_token\")`.",
                "pm.test(\"`access_token` persisted to collectionVariables\", function() {",
                "    const { access_token } = pm.response.json()",
                "    pm.collectionVariables.set(\"access_token\", access_token);",
                "});"
              ],
              "_lastExecutionId": "245f0fc7-cc02-44f0-91c2-65f915fbed80"
            }
          }
        ]
      },
      {
        "id": "91917d34-be8a-4b6e-af8d-a5f808d39ecc",
        "name": "Get Organization DIDs",
        "request": {
          "url": {
            "path": [
              "identifiers",
              "{{ORGANIZATION_DID_WEB}}"
            ],
            "host": [
              "{{API_BASE_URL}}"
            ],
            "query": [],
            "variable": []
          },
          "header": [
            {
              "key": "Accept",
              "value": "application/json"
            }
          ],
          "method": "GET",
          "auth": {
            "type": "bearer",
            "bearer": [
              {
                "type": "string",
                "value": "{{access_token}}",
                "key": "token"
              }
            ]
          }
        },
        "response": [],
        "event": [
          {
            "listen": "test",
            "script": {
              "id": "1f731e3a-bc49-4f83-bcbb-5fd1b32f784e",
              "type": "text/javascript",
              "exec": [
                "pm.test(\"Status code is 200\", function () {",
                "    pm.response.to.have.status(200);",
                "});",
                "",
                "pm.test(\"must include valid JSON response body\", function() {",
                "    pm.response.json(); // will throw on parse failure",
                "});",
                "",
                "// The response JSON must include a didDocument property that contains the",
                "// resolved DID document.",
                "pm.test(\"didDocument must be present in response body\", function() {",
                "    const jsonData = pm.response.json();",
                "    pm.expect(jsonData).to.have.property('didDocument');",
                "});",
                "",
                "// Service array is used to look up traceability API service endpoint",
                "pm.test(\"Response must include 'service' array\", function() {",
                "    const { service } = pm.response.json().didDocument;",
                "    pm.expect(service).to.be.an('array').that.is.not.empty;",
                "});",
                "",
                "// Service array must be correctly defined in DID document",
                "pm.test(\"'service' array must define Traceability API service endpoint\", function() {",
                "    const { service } = pm.response.json().didDocument;",
                "    const entry = service.find((s) => s.type == \"TraceabilityAPI\");",
                "    pm.expect(entry).to.be.an('object').that.is.not.empty;",
                "    pm.expect(entry.serviceEndpoint).to.be.a('string').that.is.not.empty;",
                "});",
                "",
                "// If a verificationMethod property is present, the controller property must",
                "// match the didDocument.id property.",
                "pm.test(\"verification method controller must match did subject\", function() {",
                "    const { didDocument } = pm.response.json();",
                "    const vm = didDocument.verificationMethod || [];",
                "    vm.forEach((m) => pm.expect(m.controller).to.equal(didDocument.id));",
                "});"
              ],
              "_lastExecutionId": "22e97c9f-3640-46e3-a71b-7bb209c264c5"
            }
          }
        ],
        "protocolProfileBehavior": {
          "disabledSystemHeaders": {}
        }
      }
    ]
  },
  "run": {
    "stats": {
      "iterations": {
        "total": 1,
        "pending": 0,
        "failed": 0
      },
      "items": {
        "total": 2,
        "pending": 0,
        "failed": 0
      },
      "scripts": {
        "total": 6,
        "pending": 0,
        "failed": 0
      },
      "prerequests": {
        "total": 2,
        "pending": 0,
        "failed": 0
      },
      "requests": {
        "total": 2,
        "pending": 0,
        "failed": 0
      },
      "tests": {
        "total": 2,
        "pending": 0,
        "failed": 0
      },
      "assertions": {
        "total": 11,
        "pending": 0,
        "failed": 0
      },
      "testScripts": {
        "total": 4,
        "pending": 0,
        "failed": 0
      },
      "prerequestScripts": {
        "total": 2,
        "pending": 0,
        "failed": 0
      }
    },
    "timings": {
      "responseAverage": 264.5,
      "responseMin": 56,
      "responseMax": 473,
      "responseSd": 208.5,
      "dnsAverage": 0,
      "dnsMin": 0,
      "dnsMax": 0,
      "dnsSd": 0,
      "firstByteAverage": 0,
      "firstByteMin": 0,
      "firstByteMax": 0,
      "firstByteSd": 0,
      "started": 1715043469879,
      "completed": 1715043470483
    },
    "executions": [
      {
        "id": "6496ad91-3674-42dd-8275-3ea13324834f",
        "cursor": {
          "position": 0,
          "iteration": 0,
          "length": 2,
          "cycles": 1,
          "empty": false,
          "eof": false,
          "bof": true,
          "cr": false,
          "ref": "56b73fd2-aad3-4053-b36a-c98b43de1888",
          "httpRequestId": "644ef6ae-819d-4c79-a6f1-630baac10188"
        },
        "item": {
          "id": "6496ad91-3674-42dd-8275-3ea13324834f",
          "name": "Get Access Token"
        },
        "response": {
          "id": "652340a5-806e-4f26-ab3e-d49f68ed0a21",
          "status": "OK",
          "code": 200,
          "responseTime": 473,
          "responseSize": 957
        },
        "assertions": [
          {
            "assertion": "must return `200 Success` status",
            "skipped": false
          },
          {
            "assertion": "response body must include non-empty access_token",
            "skipped": false
          },
          {
            "assertion": "response body must represent `Bearer` token",
            "skipped": false
          },
          {
            "assertion": "returned token must expire in the future",
            "skipped": false
          },
          {
            "assertion": "`access_token` persisted to collectionVariables",
            "skipped": false
          }
        ]
      },
      {
        "id": "91917d34-be8a-4b6e-af8d-a5f808d39ecc",
        "cursor": {
          "ref": "f1ab5fb6-30fb-4487-be06-b43a57f5e26f",
          "length": 2,
          "cycles": 1,
          "position": 1,
          "iteration": 0,
          "httpRequestId": "5935d6c3-8f3e-44b4-afc9-ae5db572c6cd"
        },
        "item": {
          "id": "91917d34-be8a-4b6e-af8d-a5f808d39ecc",
          "name": "Get Organization DIDs"
        },
        "response": {
          "id": "1c693a4f-0b69-4777-986b-9f5fb1aa950f",
          "status": "OK",
          "code": 200,
          "responseTime": 56,
          "responseSize": 1462
        },
        "assertions": [
          {
            "assertion": "Status code is 200",
            "skipped": false
          },
          {
            "assertion": "must include valid JSON response body",
            "skipped": false
          },
          {
            "assertion": "didDocument must be present in response body",
            "skipped": false
          },
          {
            "assertion": "Response must include 'service' array",
            "skipped": false
          },
          {
            "assertion": "'service' array must define Traceability API service endpoint",
            "skipped": false
          },
          {
            "assertion": "verification method controller must match did subject",
            "skipped": false
          }
        ]
      }
    ]
  }
}